soundcloud_downloader/__init__.py
soundcloud_downloader/downloader.py
soundcloud_downloader-0.1.4.dist-info/METADATA
soundcloud_downloader-0.1.4.dist-info/WHEEL
soundcloud_downloader-0.1.4.dist-info/top_level.txt
soundcloud_downloader-0.1.4.dist-info/RECORD
