Metadata-Version: 2.2
Name: soundcloud_downloader
Version: 0.1.4
Summary: A library for downloading music from SoundCloud using scdl
Home-page: https://github.com/ATHStudioo/soundcloud_downloader
Author: ATH_Studioo
Author-email: ihor6285@gmail.com
Requires-Python: >=3.6
Requires-Dist: scdl>=2.12.3
Dynamic: author
Dynamic: author-email
Dynamic: description
Dynamic: description-content-type
Dynamic: home-page
Dynamic: requires-dist
Dynamic: requires-python
Dynamic: summary
